{
  "$schema": "https://developer.microsoft.com/json-schemas/fabric/item/report/definition/visualContainer/1.5.0/schema.json",
  "name": "c0044fce0d6488c87f0e",
  "position": {
    "x": 0,
    "y": 0,
    "z": 2000,
    "height": 376.41337386018239,
    "width": 345.28875379939211,
    "tabOrder": 1000
  },
  "visual": {
    "visualType": "donutChart",
    "query": {
      "queryState": {
        "Y": {
          "projections": [
            {
              "field": {
                "Measure": {
                  "Expression": {
                    "SourceRef": {
                      "Entity": "master_529"
                    }
                  },
                  "Property": "Total New Investor"
                }
              },
              "queryRef": "master_529.Total New Investor",
              "nativeQueryRef": "Total New Investor"
            },
            {
              "field": {
                "Measure": {
                  "Expression": {
                    "SourceRef": {
                      "Entity": "master_529"
                    }
                  },
                  "Property": "Total Existing Investor"
                }
              },
              "queryRef": "master_529.Total Existing Investor",
              "nativeQueryRef": "Total Existing Investor"
            }
          ]
        }
      },
      "sortDefinition": {
        "sort": [
          {
            "field": {
              "Measure": {
                "Expression": {
                  "SourceRef": {
                    "Entity": "master_529"
                  }
                },
                "Property": "Total New Investor"
              }
            },
            "direction": "Descending"
          }
        ],
        "isDefaultSort": true
      }
    },
    "objects": {
      "legend": [
        {
          "properties": {
            "show": {
              "expr": {
                "Literal": {
                  "Value": "true"
                }
              }
            },
            "position": {
              "expr": {
                "Literal": {
                  "Value": "'BottomCenter'"
                }
              }
            },
            "showTitle": {
              "expr": {
                "Literal": {
                  "Value": "false"
                }
              }
            }
          }
        }
      ],
      "labels": [
        {
          "properties": {
            "labelStyle": {
              "expr": {
                "Literal": {
                  "Value": "'Data value, percent of total'"
                }
              }
            },
            "labelDisplayUnits": {
              "expr": {
                "Literal": {
                  "Value": "1D"
                }
              }
            },
            "labelPrecision": {
              "expr": {
                "Literal": {
                  "Value": "0L"
                }
              }
            }
          }
        }
      ],
      "dataPoint": [
        {
          "properties": {
            "fill": {
              "solid": {
                "color": {
                  "expr": {
                    "ThemeDataColor": {
                      "ColorId": 6,
                      "Percent": 0
                    }
                  }
                }
              }
            }
          },
          "selector": {
            "data": [
              {
                "scopeId": {
                  "Comparison": {
                    "ComparisonKind": 0,
                    "Left": {
                      "Column": {
                        "Expression": {
                          "SourceRef": {
                            "Entity": "master_529"
                          }
                        },
                        "Property": "FundingStatus"
                      }
                    },
                    "Right": {
                      "Literal": {
                        "Value": "'Funded'"
                      }
                    }
                  }
                }
              }
            ]
          }
        },
        {
          "properties": {
            "fill": {
              "solid": {
                "color": {
                  "expr": {
                    "ThemeDataColor": {
                      "ColorId": 1,
                      "Percent": 0.6
                    }
                  }
                }
              }
            }
          },
          "selector": {
            "data": [
              {
                "scopeId": {
                  "Comparison": {
                    "ComparisonKind": 0,
                    "Left": {
                      "Column": {
                        "Expression": {
                          "SourceRef": {
                            "Entity": "master_529"
                          }
                        },
                        "Property": "FundingStatus"
                      }
                    },
                    "Right": {
                      "Literal": {
                        "Value": "'Unfunded'"
                      }
                    }
                  }
                }
              }
            ]
          }
        },
        {
          "properties": {
            "fill": {
              "solid": {
                "color": {
                  "expr": {
                    "ThemeDataColor": {
                      "ColorId": 4,
                      "Percent": 0
                    }
                  }
                }
              }
            }
          },
          "selector": {
            "data": [
              {
                "scopeId": {
                  "Comparison": {
                    "ComparisonKind": 0,
                    "Left": {
                      "Column": {
                        "Expression": {
                          "SourceRef": {
                            "Entity": "master_529"
                          }
                        },
                        "Property": "AccountStatus"
                      }
                    },
                    "Right": {
                      "Literal": {
                        "Value": "'Existing'"
                      }
                    }
                  }
                }
              }
            ]
          }
        },
        {
          "properties": {
            "fill": {
              "solid": {
                "color": {
                  "expr": {
                    "ThemeDataColor": {
                      "ColorId": 7,
                      "Percent": 0
                    }
                  }
                }
              }
            }
          },
          "selector": {
            "data": [
              {
                "scopeId": {
                  "Comparison": {
                    "ComparisonKind": 0,
                    "Left": {
                      "Column": {
                        "Expression": {
                          "SourceRef": {
                            "Entity": "master_529"
                          }
                        },
                        "Property": "AccountStatus"
                      }
                    },
                    "Right": {
                      "Literal": {
                        "Value": "'New'"
                      }
                    }
                  }
                }
              }
            ]
          }
        },
        {
          "properties": {
            "fill": {
              "solid": {
                "color": {
                  "expr": {
                    "ThemeDataColor": {
                      "ColorId": 7,
                      "Percent": 0
                    }
                  }
                }
              }
            }
          },
          "selector": {
            "metadata": "master_529.Total New Investor"
          }
        },
        {
          "properties": {
            "fill": {
              "solid": {
                "color": {
                  "expr": {
                    "ThemeDataColor": {
                      "ColorId": 2,
                      "Percent": 0
                    }
                  }
                }
              }
            }
          },
          "selector": {
            "metadata": "master_529.Total Existing Investor"
          }
        }
      ]
    },
    "visualContainerObjects": {
      "title": [
        {
          "properties": {
            "show": {
              "expr": {
                "Literal": {
                  "Value": "true"
                }
              }
            },
            "text": {
              "expr": {
                "Literal": {
                  "Value": "'Overall Analysis'"
                }
              }
            },
            "alignment": {
              "expr": {
                "Literal": {
                  "Value": "'center'"
                }
              }
            }
          }
        }
      ]
    },
    "drillFilterOtherVisuals": true
  },
  "parentGroupName": "d1e80ee29602e58816d9"
}